deckz/__init__.py
deckz/analyzing/__init__.py
deckz/analyzing/sections_analyzer.py
deckz/cli/__init__.py
deckz/cli/asset_deps.py
deckz/cli/asset_search.py
deckz/cli/check_all.py
deckz/cli/clean.py
deckz/cli/clean_all.py
deckz/cli/deps.py
deckz/cli/extras/__init__.py
deckz/cli/extras/issue.py
deckz/cli/extras/random.py
deckz/cli/extras/upload.py
deckz/cli/generate_completion.py
deckz/cli/print_settings.py
deckz/cli/print_variables.py
deckz/cli/run.py
deckz/cli/tree.py
deckz/cli/upgrade.py
deckz/cli/watch.py
deckz/components/__init__.py
deckz/components/assets_analyzer.py
deckz/components/assets_builder.py
deckz/components/assets_metadata_retriever.py
deckz/components/assets_searcher.py
deckz/components/compiler.py
deckz/components/deck_builder.py
deckz/components/factory.py
deckz/components/parser.py
deckz/components/protocols.py
deckz/components/renderer.py
deckz/configuring/__init__.py
deckz/configuring/settings.py
deckz/configuring/variables.py
deckz/exceptions.py
deckz/extras/__init__.py
deckz/extras/github_querying.py
deckz/extras/mailing.py
deckz/extras/uploading.py
deckz/models.py
deckz/pipelines.py
deckz/py.typed
deckz/utils.py
deckz-24.3.0.dist-info/WHEEL
deckz-24.3.0.dist-info/entry_points.txt
deckz-24.3.0.dist-info/METADATA
deckz-24.3.0.dist-info/RECORD
