Metadata-Version: 2.3
Name: deckz
Version: 24.3.0
Summary: Tool to handle multiple beamer decks.
Author: m09, NyxAether
Author-email: m09 <142691+m09@users.noreply.github.com>, NyxAether <contact.nyxhemera@gmail.com>
Classifier: Topic :: Software Development :: Build Tools
Classifier: License :: OSI Approved :: Apache Software License
Requires-Dist: appdirs>=1,<2
Requires-Dist: cyclopts>=4,<5
Requires-Dist: email-validator>=2,<3
Requires-Dist: google-api-python-client>=2,<3
Requires-Dist: google-auth-oauthlib>=1,<2
Requires-Dist: jinja2>=3,<4
Requires-Dist: kaleido>=1,<2
Requires-Dist: matplotlib>=3,<4
Requires-Dist: niquests>=3,<4
Requires-Dist: plotly>=6,<7
Requires-Dist: pydantic>=2,<3
Requires-Dist: pygit2>=1,<2
Requires-Dist: pyyaml>=6,<7
Requires-Dist: rich>=14,<15
Requires-Dist: sendgrid>=6,<7
Requires-Dist: typer>=0.13,<1
Requires-Dist: watchfiles>=1,<2
Requires-Python: >=3.12
